{
	"version":1.0,
	"people":[
		{
			"pose_keypoints":[
				0,0,0,0,0,0,0,0,0,0,0,0,0,0,0,0,0,0,0,0,0,0,0,0,1878.22,472.522,0.540005,1872.35,622.189,0.771077,1749.16,719.103,0.799344,0,0,0,0,0,0,0,0,0,0,0,0,0,0,0,0,0,0,0,0,0
			],
			"face_keypoints":[
				
			],
			"hand_left_keypoints":[
				
			],
			"hand_right_keypoints":[
				
			]
		},
		{
			"pose_keypoints":[
				0,0,0,0,0,0,0,0,0,0,0,0,0,0,0,0,0,0,0,0,0,0,0,0,0,0,0,0,0,0,0,0,0,1916.47,472.496,0.172337,1916.43,633.874,0.396255,1916.42,760,0.609096,0,0,0,0,0,0,0,0,0,0,0,0
			],
			"face_keypoints":[
				
			],
			"hand_left_keypoints":[
				
			],
			"hand_right_keypoints":[
				
			]
		}
	]
}
