{
	"version":1.0,
	"people":[
		{
			"pose_keypoints":[
				0,0,0,0,0,0,0,0,0,0,0,0,0,0,0,0,0,0,0,0,0,0,0,0,1141.66,466.668,0.56576,1100.55,619.26,0.696501,1041.74,768.985,0.76661,0,0,0,0,0,0,0,0,0,0,0,0,0,0,0,0,0,0,0,0,0
			],
			"face_keypoints":[
				
			],
			"hand_left_keypoints":[
				
			],
			"hand_right_keypoints":[
				
			]
		},
		{
			"pose_keypoints":[
				1162.19,176.05,0.524171,0,0,0,1115.2,267.097,0.851773,0,0,0,0,0,0,0,0,0,0,0,0,0,0,0,0,0,0,0,0,0,0,0,0,0,0,0,0,0,0,0,0,0,1150.45,170.105,0.834995,1176.76,155.599,0.131996,1115.2,179.056,0.939411,0,0,0
			],
			"face_keypoints":[
				
			],
			"hand_left_keypoints":[
				
			],
			"hand_right_keypoints":[
				
			]
		}
	]
}
