{
	"version":1.0,
	"people":[
		{
			"pose_keypoints":[
				0,0,0,0,0,0,0,0,0,0,0,0,0,0,0,0,0,0,0,0,0,0,0,0,1018.29,469.55,0.564194,968.385,619.297,0.719559,903.979,760.104,0.764866,0,0,0,0,0,0,0,0,0,0,0,0,0,0,0,0,0,0,0,0,0
			],
			"face_keypoints":[
				
			],
			"hand_left_keypoints":[
				
			],
			"hand_right_keypoints":[
				
			]
		},
		{
			"pose_keypoints":[
				1044.91,196.678,0.320275,0,0,0,1006.66,264.071,0.666678,0,0,0,0,0,0,0,0,0,0,0,0,0,0,0,0,0,0,0,0,0,0,0,0,0,0,0,0,0,0,0,0,0,1041.8,176.16,0.509147,1068.22,176.051,0.0993509,1021.33,193.653,0.641382,0,0,0
			],
			"face_keypoints":[
				
			],
			"hand_left_keypoints":[
				
			],
			"hand_right_keypoints":[
				
			]
		}
	]
}
